{"version":1,"resource":"vscode-remote://ssh-remote%2Bcmsc508.com/home/24SP/24SP_dominguezjs/public_html/schema","entries":[{"id":"FNlm","timestamp":1712186312514},{"id":"JLMM","timestamp":1712368546340},{"id":"HiQi","timestamp":1714267211573},{"id":"1FS0","timestamp":1714524383081},{"id":"WDXb","timestamp":1714679725016},{"id":"0yzf","timestamp":1714680603836},{"id":"2ce1","timestamp":1714699049496},{"id":"qM3a","timestamp":1714860853521},{"id":"T6Bj","timestamp":1714861130156},{"id":"FITH","timestamp":1714861571783},{"id":"Ovc4","timestamp":1714861586872},{"id":"uB73","source":"undoRedo.source","timestamp":1714861622268},{"id":"XvqO","timestamp":1714861662467},{"id":"5bQ8","timestamp":1714870831523},{"id":"tTls","timestamp":1714918438081},{"id":"UFF1","timestamp":1714918620524},{"id":"TtJI","timestamp":1714918682341},{"id":"rX1c","timestamp":1714918861816},{"id":"vMmj","source":"undoRedo.source","timestamp":1714919344210},{"id":"jn9J","timestamp":1714919348200},{"id":"SBEe","timestamp":1714919400412},{"id":"BR1Q","timestamp":1714919455976},{"id":"o805","timestamp":1714919472149},{"id":"XnqF","source":"undoRedo.source","timestamp":1714919474040},{"id":"mATk","timestamp":1714919490164},{"id":"tEDk","timestamp":1714948117022},{"id":"3Xbw","timestamp":1714966117580},{"id":"oG0j","source":"localHistoryRestore.source","timestamp":1714966196422}]}